pyrho/UI.py
pyrho/__init__.py
pyrho/runPyRho.py
pyrhoM-0.0.3.1.dist-info/LICENSE
pyrhoM-0.0.3.1.dist-info/METADATA
pyrhoM-0.0.3.1.dist-info/WHEEL
pyrhoM-0.0.3.1.dist-info/top_level.txt
pyrhoM-0.0.3.1.dist-info/RECORD
